LICENSE
MANIFEST.in
README.md
setup.py
bin/opsbro
data/global-configuration/keys/mfkey.priv
data/global-configuration/keys/mfkey.pub
data/global-configuration/packs/apache/package.yml
data/global-configuration/packs/apache/collectors/__init__.py
data/global-configuration/packs/apache/collectors/collector_apache.py
data/global-configuration/packs/apache/parameters/parameters.yml
data/global-configuration/packs/core-cli-agent/package.yml
data/global-configuration/packs/core-cli-agent/cli/__init__.py
data/global-configuration/packs/core-cli-agent/cli/cli.py
data/global-configuration/packs/core-cli-collectors/package.yml
data/global-configuration/packs/core-cli-collectors/cli/__init__.py
data/global-configuration/packs/core-cli-collectors/cli/cli.py
data/global-configuration/packs/core-cli-detectors/package.yml
data/global-configuration/packs/core-cli-detectors/cli/__init__.py
data/global-configuration/packs/core-cli-detectors/cli/cli.py
data/global-configuration/packs/core-cli-evaluators/package.yml
data/global-configuration/packs/core-cli-evaluators/cli/__init__.py
data/global-configuration/packs/core-cli-evaluators/cli/cli.py
data/global-configuration/packs/core-cli-packs/package.yml
data/global-configuration/packs/core-cli-packs/cli/__init__.py
data/global-configuration/packs/core-cli-packs/cli/cli.py
data/global-configuration/packs/core-functions/package.yml
data/global-configuration/packs/core-functions/module/__init__.py
data/global-configuration/packs/core-functions/module/filesystem.py
data/global-configuration/packs/core-functions/module/filesystem.txt
data/global-configuration/packs/core-functions/module/fldap.py
data/global-configuration/packs/core-functions/module/fstrings.py
data/global-configuration/packs/core-functions/module/ftimes.py
data/global-configuration/packs/core-functions/module/logic.py
data/global-configuration/packs/core-functions/module/module.py
data/global-configuration/packs/core-functions/module/network.py
opsbro.egg-info/PKG-INFO
opsbro.egg-info/SOURCES.txt
opsbro.egg-info/dependency_links.txt
opsbro.egg-info/not-zip-safe
opsbro.egg-info/top_level.txt
